{
    "items": [
        {
            "project": "en.wikipedia",
            "article": "Gina_Pell\u00f3n",
            "granularity": "monthly",
            "timestamp": "2022010100",
            "access": "all-access",
            "agent": "user",
            "views": 49
        },
        {
            "project": "en.wikipedia",
            "article": "Gina_Pell\u00f3n",
            "granularity": "monthly",
            "timestamp": "2022020100",
            "access": "all-access",
            "agent": "user",
            "views": 72
        },
        {
            "project": "en.wikipedia",
            "article": "Gina_Pell\u00f3n",
            "granularity": "monthly",
            "timestamp": "2022030100",
            "access": "all-access",
            "agent": "user",
            "views": 57
        },
        {
            "project": "en.wikipedia",
            "article": "Gina_Pell\u00f3n",
            "granularity": "monthly",
            "timestamp": "2022040100",
            "access": "all-access",
            "agent": "user",
            "views": 65
        },
        {
            "project": "en.wikipedia",
            "article": "Gina_Pell\u00f3n",
            "granularity": "monthly",
            "timestamp": "2022050100",
            "access": "all-access",
            "agent": "user",
            "views": 65
        },
        {
            "project": "en.wikipedia",
            "article": "Gina_Pell\u00f3n",
            "granularity": "monthly",
            "timestamp": "2022060100",
            "access": "all-access",
            "agent": "user",
            "views": 54
        },
        {
            "project": "en.wikipedia",
            "article": "Gina_Pell\u00f3n",
            "granularity": "monthly",
            "timestamp": "2022070100",
            "access": "all-access",
            "agent": "user",
            "views": 49
        },
        {
            "project": "en.wikipedia",
            "article": "Gina_Pell\u00f3n",
            "granularity": "monthly",
            "timestamp": "2022080100",
            "access": "all-access",
            "agent": "user",
            "views": 55
        },
        {
            "project": "en.wikipedia",
            "article": "Gina_Pell\u00f3n",
            "granularity": "monthly",
            "timestamp": "2022090100",
            "access": "all-access",
            "agent": "user",
            "views": 77
        },
        {
            "project": "en.wikipedia",
            "article": "Gina_Pell\u00f3n",
            "granularity": "monthly",
            "timestamp": "2022100100",
            "access": "all-access",
            "agent": "user",
            "views": 62
        },
        {
            "project": "en.wikipedia",
            "article": "Gina_Pell\u00f3n",
            "granularity": "monthly",
            "timestamp": "2022110100",
            "access": "all-access",
            "agent": "user",
            "views": 70
        },
        {
            "project": "en.wikipedia",
            "article": "Gina_Pell\u00f3n",
            "granularity": "monthly",
            "timestamp": "2022120100",
            "access": "all-access",
            "agent": "user",
            "views": 76
        }
    ]
}