{
    "items": [
        {
            "project": "en.wikipedia",
            "article": "Pietro_Longhi",
            "granularity": "monthly",
            "timestamp": "2022010100",
            "access": "all-access",
            "agent": "user",
            "views": 807
        },
        {
            "project": "en.wikipedia",
            "article": "Pietro_Longhi",
            "granularity": "monthly",
            "timestamp": "2022020100",
            "access": "all-access",
            "agent": "user",
            "views": 787
        },
        {
            "project": "en.wikipedia",
            "article": "Pietro_Longhi",
            "granularity": "monthly",
            "timestamp": "2022030100",
            "access": "all-access",
            "agent": "user",
            "views": 663
        },
        {
            "project": "en.wikipedia",
            "article": "Pietro_Longhi",
            "granularity": "monthly",
            "timestamp": "2022040100",
            "access": "all-access",
            "agent": "user",
            "views": 716
        },
        {
            "project": "en.wikipedia",
            "article": "Pietro_Longhi",
            "granularity": "monthly",
            "timestamp": "2022050100",
            "access": "all-access",
            "agent": "user",
            "views": 711
        },
        {
            "project": "en.wikipedia",
            "article": "Pietro_Longhi",
            "granularity": "monthly",
            "timestamp": "2022060100",
            "access": "all-access",
            "agent": "user",
            "views": 631
        },
        {
            "project": "en.wikipedia",
            "article": "Pietro_Longhi",
            "granularity": "monthly",
            "timestamp": "2022070100",
            "access": "all-access",
            "agent": "user",
            "views": 712
        },
        {
            "project": "en.wikipedia",
            "article": "Pietro_Longhi",
            "granularity": "monthly",
            "timestamp": "2022080100",
            "access": "all-access",
            "agent": "user",
            "views": 703
        },
        {
            "project": "en.wikipedia",
            "article": "Pietro_Longhi",
            "granularity": "monthly",
            "timestamp": "2022090100",
            "access": "all-access",
            "agent": "user",
            "views": 813
        },
        {
            "project": "en.wikipedia",
            "article": "Pietro_Longhi",
            "granularity": "monthly",
            "timestamp": "2022100100",
            "access": "all-access",
            "agent": "user",
            "views": 704
        },
        {
            "project": "en.wikipedia",
            "article": "Pietro_Longhi",
            "granularity": "monthly",
            "timestamp": "2022110100",
            "access": "all-access",
            "agent": "user",
            "views": 943
        },
        {
            "project": "en.wikipedia",
            "article": "Pietro_Longhi",
            "granularity": "monthly",
            "timestamp": "2022120100",
            "access": "all-access",
            "agent": "user",
            "views": 686
        }
    ]
}